metacognition/__init__.py
metacognition-0.0.0.dist-info/METADATA
metacognition-0.0.0.dist-info/WHEEL
metacognition-0.0.0.dist-info/top_level.txt
metacognition-0.0.0.dist-info/RECORD
